AUTHORS
CHANGELOG.txt
DESCRIPTION
LICENSE
MANIFEST.in
README.rst
setup.py
cmsplugin_blog_images/__init__.py
cmsplugin_blog_images/admin.py
cmsplugin_blog_images/models.py
cmsplugin_blog_images.egg-info/PKG-INFO
cmsplugin_blog_images.egg-info/SOURCES.txt
cmsplugin_blog_images.egg-info/dependency_links.txt
cmsplugin_blog_images.egg-info/top_level.txt
cmsplugin_blog_images/migrations/0001_initial.py
cmsplugin_blog_images/migrations/__init__.py
cmsplugin_blog_images/templatetags/__init__.py
cmsplugin_blog_images/templatetags/cmsplugin_blog_images_tags.py
cmsplugin_blog_images/tests/__init__.py
cmsplugin_blog_images/tests/runtests.py
cmsplugin_blog_images/tests/south_settings.py
cmsplugin_blog_images/tests/test_settings.py
cmsplugin_blog_images/tests/urls.py
cmsplugin_blog_images/tests/test_app/__init__.py
cmsplugin_blog_images/tests/test_app/models.py
cmsplugin_blog_images/tests/test_app/templates/base.html
cmsplugin_blog_images/tests/test_app/templates/cms/home.html