Metadata-Version: 1.0
Name: cmsplugin-blog-images
Version: 0.1
Summary: Extension for cmsplugin-blog which adds images to blog entries.
